LICENSE
MANIFEST.in
README.rst
madseq.py
setup.py
madseq.egg-info/PKG-INFO
madseq.egg-info/SOURCES.txt
madseq.egg-info/dependency_links.txt
madseq.egg-info/entry_points.txt
madseq.egg-info/requires.txt
madseq.egg-info/top_level.txt
test/test_document.py
test/test_e2e.py
test/test_element.py
test/test_regex.py
test/test_transform.py
test/test_util.py
test/test_value.py