Metadata-Version: 1.1
Name: madseq
Version: 0.4.4
Summary: Parser/transformator for MAD-X sequences
Home-page: https://github.com/coldfix/madseq
Author: Thomas Gläßle
Author-email: t_glaessle@gmx.de
License: MIT
Platform: UNKNOWN
Classifier: Development Status :: 3 - Alpha
Classifier: Intended Audience :: Developers
Classifier: Intended Audience :: Science/Research
Classifier: License :: OSI Approved :: MIT License
Classifier: Operating System :: OS Independent
Classifier: Programming Language :: Python
Classifier: Topic :: Scientific/Engineering :: Medical Science Apps.
Classifier: Topic :: Scientific/Engineering :: Physics
